brain_proxy/__init__.py
brain_proxy/__version__.py
brain_proxy/brain_proxy.py
brain_proxy/brain_proxy2.py
brain_proxy/brain_proxy_langchain.py
brain_proxy/chroma_adapter.py
brain_proxy/temporal_utils.py
brain_proxy/tools.py
brain_proxy/upstash_adapter.py
brain_proxy-0.1.96.dist-info/METADATA
brain_proxy-0.1.96.dist-info/WHEEL
brain_proxy-0.1.96.dist-info/top_level.txt
brain_proxy-0.1.96.dist-info/RECORD
