Metadata-Version: 2.4
Name: brain-proxy
Version: 0.1.96
Summary: OpenAI-compatible FastAPI router with Chroma + LangMem memory.
Home-page: https://github.com/puntorigen/brain-proxy
Author: Pablo Schaffner
Author-email: Pablo Schaffner <pablo@puntorigen.com>
Project-URL: Homepage, https://github.com/puntorigen/brain-proxy
Requires-Python: >=3.8
Requires-Dist: fastapi<1.0.0,>=0.104.1
Requires-Dist: openai<2.0.0,>=1.68.2
Requires-Dist: langchain-chroma>=0.1.0
Requires-Dist: langmem>=0.0.29
Requires-Dist: tiktoken>=0.7.0
Requires-Dist: pydantic<3.0.0,>=2.5.0
Requires-Dist: langchain-openai>=0.1.0
Requires-Dist: numpy<2.0.0,>=1.24.0
Requires-Dist: litellm>=1.70.0
Requires-Dist: langchain-litellm>=0.1.0
Requires-Dist: dateparser>=1.1.0
Requires-Dist: async-promptic>=5.0.0
Requires-Dist: httpx>=0.24.0
Requires-Dist: upstash-vector>=0.1.0
Dynamic: author
Dynamic: home-page
Dynamic: requires-python
